{
   "title": "Aufschüttung",
   "keywords": [
      "Seeufer",
      "Aufschüttung"
   ],
   "metadata_date": "2022-05-24T11:45:02",
   "updateFrequency": "monthly",
   "purpose": "stadtinterne Publikation",
   "abstract": "Aufbereitung des Geodatensatzes \"Aufschüttung\" für den Geoserver.\n\nSiehe dort für einen inhaltlichen Beschrieb.",
   "identificationDate": "2023-05-12",
   "identificationDateType": "revision",
   "responsibleParty": "Stadt Zürich - Hochbaudepartement - Amt für Städtebau",
   "contactPerson": "Janine Sutter",
   "referenceSystem": "CH1903+_LV95",
   "boundingBox": {
      "westBoundLongitude": 8.443821782566665,
      "eastBoundLongitude": 8.631776103472221,
      "southBoundLatitude": 47.31549273037445,
      "northBoundLatitude": 47.43963707749998
   },
   "distributionFormats": [
      "ESRI Shape (.shp)",
      "GeoJSON (.json)",
      "Geopackage (.gpkg)",
      "DXF (.dxf)"
   ],
   "downloadURL": "https://www.stadt-zuerich.ch/geodaten/download/Aufschuettung",
   "contentInfo": {
      "descriptionsIncludedWithDataset": false,
      "classes": [
         {
            "name": "AFS_SDE.AUFSCHUETTUNG_A",
            "description": null,
            "attributes": [
               {
                  "name": "GEOMETRIE",
                  "description": null
               },
               {
                  "name": "OBJECTID",
                  "description": null
               }
            ]
         }
      ]
   }
}