{
   "title": "Vornamen neugeborener Mädchen und Knaben mit Wohnsitz in der Stadt Zürich",
   "downloadURL": "https://data.stadt-zuerich.ch/dataset/bev_vornamen_baby_od3700",
   "abstract": "Alle nach Geschlecht und Geburtsjahr aggregierten Vornamen von Neugeborenen mit Wohnsitz in der Stadt Zürich.",
   "distributionFormats": [
      "Comma Separated Values (.csv)"
   ],
   "purpose": "Weitere Daten zu Vornamen:\n\nWeitere Daten zu Vornamen finden Sie unter:\n\nZweite Vornamen Neugeborene\nVornamen der aktuellen Wohnbevölkerung",
   "contentInfo": {
      "classes": [
         {
            "name": "Vornamen neugeborener Mädchen und Knaben mit Wohnsitz in der Stadt Zürich",
            "description": "",
            "attributes": [
               {
                  "name": "Jahrgang (technisch: StichtagDatJahr)",
                  "description": "Geburtsjahr (num)."
               },
               {
                  "name": "Vorname (technisch: Vorname)",
                  "description": "Vorname des Neugeborenen (char)."
               },
               {
                  "name": "Geschlecht (technisch: SexLang)",
                  "description": "Geschlecht (char). [Werte: weiblich, männlich]."
               },
               {
                  "name": "Anzahl (technisch: AnzGebuWir)",
                  "description": "Anzahl Neugeborene aus der wirtschaftlichen Wohnbevölkerung der Stadt Zürich (num)."
               }
            ]
         }
      ]
   },
   "identificationDate": "2025-04-30"
}