{
   "title": "Bevölkerung nach Zivilstand, Geschlecht, Alter und Stadtquartier",
   "downloadURL": "https://data.stadt-zuerich.ch/dataset/bev_bestand_jahr_quartier_zivilstand_ag_geschl_od3310",
   "abstract": "Zivilstand der Bevölkerung nach Geschlecht, Alter und Stadtquartier.",
   "distributionFormats": [
      "Comma Separated Values (.csv)"
   ],
   "purpose": "",
   "contentInfo": {
      "classes": [
         {
            "name": "Bevölkerung nach Zivilstand, Geschlecht, Alter und Stadtquartier",
            "description": "",
            "attributes": [
               {
                  "name": "Ereignisjahr (technisch: StichtagDatJahr)",
                  "description": "Jahr (Integer)."
               },
               {
                  "name": "Alter (Sort) (technisch: AlterVSort)",
                  "description": "Alter (Integer)."
               },
               {
                  "name": "Alter (Cd) (technisch: AlterVCd)",
                  "description": "Alter (Integer, Code)."
               },
               {
                  "name": "5-Jahres-Altersgruppe (Sort) (technisch: AlterV05Sort)",
                  "description": "Sortierschlüssel für die Altersgruppe (Numerisch)."
               },
               {
                  "name": "5-Jahres-Altersgruppe (Code) (technisch: AlterV05Cd)",
                  "description": "Code für die Altersgruppe (Numerisch)."
               },
               {
                  "name": "5-Jahres-Altersgruppe (technisch: AlterV05Kurz)",
                  "description": "5-Jahres-Altersgruppe (z.B. 0-4, 5-10, etc.)"
               },
               {
                  "name": "10-Jahres-Altersgruppe (Sort) (technisch: AlterV10Sort)",
                  "description": "Sortierschlüssel für die Altersgruppe (Numerisch)."
               },
               {
                  "name": "10-Jahres-Altersgruppe (Code) (technisch: AlterV10Cd)",
                  "description": "Code für die Altersgruppe (Numerisch)."
               },
               {
                  "name": "10-Jahres-Altersgruppe (technisch: AlterV10Kurz)",
                  "description": "10-Jahres-Altersgruppe (z.B. 0-9, 10-19, etc.)"
               },
               {
                  "name": "20-Jahres-Altersgruppe (Sort) (technisch: AlterV20Sort)",
                  "description": "Sortierschlüssel für die Altersgruppe (Numerisch)."
               },
               {
                  "name": "20-Jahres-Altersgruppe (Code) (technisch: AlterV20Cd)",
                  "description": "Code für die Altersgruppe (Numerisch)."
               },
               {
                  "name": "20-Jahres-Altersgruppe (technisch: AlterV20Kurz)",
                  "description": "20-Jahres-Altersgruppe (z.B. 0-19, 20-29, etc.)"
               },
               {
                  "name": "Geschlecht (Code) (technisch: SexCd)",
                  "description": "Geschlecht (String)."
               },
               {
                  "name": "Geschlecht (lang) (technisch: SexLang)",
                  "description": "Geschlecht (String)."
               },
               {
                  "name": "Stadtkreis (Code) (technisch: KreisCd)",
                  "description": "Stadtkreis (Integer, Code)."
               },
               {
                  "name": "Stadtkreis (lang) (technisch: KreisLang)",
                  "description": "Stadtkreis (String)."
               },
               {
                  "name": "Stadtquartier (Sort) (technisch: QuarSort)",
                  "description": "Stadtquartier (Integer)."
               },
               {
                  "name": "Stadtquartier (Code) (technisch: QuarCd)",
                  "description": "Stadtquartier (Integer, Code)."
               },
               {
                  "name": "Stadtquartier (lang) (technisch: QuarLang)",
                  "description": "Stadtquartier (String)."
               },
               {
                  "name": "Zivilstand (gruppiert) (Sort) (technisch: Ziv2Sort)",
                  "description": "Zivilstand, Sortierschlüssel der Gruppierung (Integer)."
               },
               {
                  "name": "Zivilstand (gruppiert) (Code) (technisch: Ziv2Cd)",
                  "description": "Zivilstand, Code der Gruppierung (Integer)."
               },
               {
                  "name": "Zivilstand (gruppiert) (Lang) (technisch: Ziv2Lang)",
                  "description": "Zivilstand gruppiert. (Werte: 1 - Ledig, 2 - Verheiratet, 3 - Geschieden, 4 - Verwitwet, 5 - In eingetragener Partnerschaft, 6 - In aufgelöster Partnerschaft, 9 - Unbekannt)."
               },
               {
                  "name": "Wirtschaftliche Bevölkerung (technisch: AnzBestWir)",
                  "description": "Wirtschaftliche Bevölkerung (Integer)."
               }
            ]
         }
      ]
   },
   "identificationDate": "2025-03-05"
}