{
   "title": "Beteiligung am Urnengang der Kantons- und Regierungsratswahlen nach Alter und Geschlecht",
   "downloadURL": "https://data.stadt-zuerich.ch/dataset/politik_kantonsratswahlen_btg_urnengang_alter_geschl_od7029",
   "abstract": "Die hier ausgewiesenen Zahlen entsprechen der Anzahl eingegangener Stimmrechtsausweise den Kantons- und Regierungsratswahlen aufgeschlüsselt nach Geschlecht und Alter.",
   "distributionFormats": [
      "Comma Separated Values (.csv)"
   ],
   "purpose": "Wichtige Hinweise:\n\nDie Daten beruhen auf den eingereichten Einmalstimmrechtsausweisen (ESRA). Auf diesen ist ein persönlicher Code aufgedruckt. Dieser wurde mit einem Auszug aus dem Personenregister verglichen, der alle stimmberechtigten Personen enthält. Die ESRA werden getrennt von den Wahl- und Abstimmungsdokumenten erfasst und die gewonnen Daten anonymisiert. Auf diese Art kann bestimmt werden, wer am Urnengang teilgenommen hat, nicht aber, ob diese Personen an der Kantonsrats- oder der Regierungsratswahl teilgenommen haben. Auch ist nicht ersichtlich, wen die Personen gewählt haben.\n\nZur «Beteiligung am Urnengang»:\n\nDie Beteiligung am Urnengang stellt den Prozentanteil der abgegebenen gültigen und ungültigen Stimmrechtsausweise an allen Stimmberechtigten dar.",
   "contentInfo": {
      "classes": [
         {
            "name": "Beteiligung am Urnengang der Kantons- und Regierungsratswahlen nach Alter und Geschlecht",
            "description": "",
            "attributes": [
               {
                  "name": "Jahr (technisch: Jahr)",
                  "description": "Jahr (Numeric)"
               },
               {
                  "name": "Vollendetes Alter (Code) (technisch: AlterVCd)",
                  "description": "Vollendetes Alter (Numeric)"
               },
               {
                  "name": "Geschlecht (Lang) (technisch: SexLang)",
                  "description": "Geschlecht (String)"
               },
               {
                  "name": "Anteil in Prozent (technisch: Anteil)",
                  "description": "Anteil in Prozent (Numeric)"
               }
            ]
         }
      ]
   },
   "identificationDate": "2024-09-19"
}